tanktools/__init__.py
tanktools/_version.py
tanktools/har2ammo.py
tanktools/pcap2ammo.py
tanktools/phout.py
tanktools-1.0.9.dist-info/METADATA
tanktools-1.0.9.dist-info/RECORD
tanktools-1.0.9.dist-info/WHEEL
tanktools-1.0.9.dist-info/entry_points.txt
tanktools-1.0.9.dist-info/top_level.txt
