Metadata-Version: 2.1
Name: tanktools
Version: 1.0.9
Summary: Yandex-tank tools
Home-page: https://github.com/gaainf/tanktools
Author: Alexander Grechin
Author-email: infinum@mail.ru
License: BSD-3-Clause
Download-URL: https://github.com/gaainf/tanktools
Keywords: yandextank yandex-tank statistics tools utilities
Platform: UNKNOWN
Classifier: Development Status :: 4 - Beta
Classifier: Operating System :: OS Independent
Classifier: Environment :: Console
Classifier: Intended Audience :: Developers
Classifier: License :: OSI Approved :: BSD License
Classifier: Programming Language :: Python :: 2.7
Classifier: Programming Language :: Python :: 3.5
Classifier: Programming Language :: Python :: 3.6
Classifier: Topic :: Software Development
Classifier: Topic :: Utilities
Requires-Dist: python-dateutil (>=2.8.0)
Requires-Dist: pandas (>=0.23.4)
Requires-Dist: flake8 (>=3.5.0)
Requires-Dist: pcaper (>=1.0.2)
